vision_mech_interp_attn_head/__init__.py
vision_mech_interp_attn_head/ablation_analysis.py
vision_mech_interp_attn_head/baseline_analysis.py
vision_mech_interp_attn_head/dataset.py
vision_mech_interp_attn_head/distribution_comparison.py
vision_mech_interp_attn_head/distribution_extraction.py
vision_mech_interp_attn_head/evaluation.py
vision_mech_interp_attn_head/model.py
vision_mech_interp_attn_head/utils.py
vision_mech_interp_attn_head/visualization.py
vision_mech_interp_attn_head-0.1.8.dist-info/METADATA
vision_mech_interp_attn_head-0.1.8.dist-info/WHEEL
vision_mech_interp_attn_head-0.1.8.dist-info/top_level.txt
vision_mech_interp_attn_head-0.1.8.dist-info/RECORD
